hello_world.py
example_publish_pypi_devterminal-2.0.dist-info/LICENSE.txt
example_publish_pypi_devterminal-2.0.dist-info/METADATA
example_publish_pypi_devterminal-2.0.dist-info/WHEEL
example_publish_pypi_devterminal-2.0.dist-info/top_level.txt
example_publish_pypi_devterminal-2.0.dist-info/RECORD
