Metadata-Version: 2.1
Name: example-publish-pypi-devterminal
Version: 2.0
Summary: UNKNOWN
Home-page: https://github.com/Eng-Ahmad-Almohammad/pypi-test
Author: Ahmad Almohammad
Author-email: almohammedahmed23@gmail.com
License: MIT
Keywords: example project
Platform: UNKNOWN
License-File: LICENSE.txt
Requires-Dist: blessings (~=1.7)
